pyats_parser/__init__.py
pyats_parser/parser.py
pyats_parser-1.0.7.dist-info/LICENSE
pyats_parser-1.0.7.dist-info/METADATA
pyats_parser-1.0.7.dist-info/WHEEL
pyats_parser-1.0.7.dist-info/top_level.txt
pyats_parser-1.0.7.dist-info/RECORD
