Metadata-Version: 2.1
Name: pyats-parser
Version: 1.0.7
Summary: Parse CLI output with pyATS/Genie Librairies
Home-page: https://github.com/rtrjl/pyats_parser
Author: Rodolphe Trujillo
Author-email: rodtruji@cisco.com
License: Cisco Sample Code License, Version 1.1
Classifier: Topic :: System :: Networking
License-File: LICENSE
Requires-Dist: pyats (>22)
Requires-Dist: genie (>22)
